LICENSE
MANIFEST.in
README.rst
ez_setup.py
jcchess.desktop
jcchess.png
run.py
setup.py
chess/__init__.py
chess/pgn.py
jcchess/__init__.py
jcchess/board.py
jcchess/comments.py
jcchess/constants.py
jcchess/drag_and_drop.py
jcchess/engine_debug.py
jcchess/engine_manager.py
jcchess/engine_output.py
jcchess/gamelist.py
jcchess/gui.py
jcchess/gv.py
jcchess/jcchess.py
jcchess/load_save.py
jcchess/move_list.py
jcchess/pieces.py
jcchess/set_board_colours.py
jcchess/time_control.py
jcchess/uci.py
jcchess/utils.py
jcchess.egg-info/PKG-INFO
jcchess.egg-info/SOURCES.txt
jcchess.egg-info/dependency_links.txt
jcchess.egg-info/entry_points.txt
jcchess.egg-info/not-zip-safe
jcchess.egg-info/top_level.txt
jcchess/glade/comments.glade
jcchess/glade/common_engine_settings.glade
jcchess/glade/engine_debug.glade
jcchess/glade/engine_output.glade
jcchess/glade/gamelist.glade
jcchess/glade/main_window.glade
jcchess/glade/move_list.glade
jcchess/glade/preferences.glade
jcchess/glade/promotion.glade
jcchess/images/logo.png
jcchess/images/wood1.png
jcchess/images/wood1_hl.png
jcchess/images/pieceset1/bishopB.svg
jcchess/images/pieceset1/bishopW.svg
jcchess/images/pieceset1/kingB.svg
jcchess/images/pieceset1/kingW.svg
jcchess/images/pieceset1/knightB.svg
jcchess/images/pieceset1/knightW.svg
jcchess/images/pieceset1/pawnB.svg
jcchess/images/pieceset1/pawnW.svg
jcchess/images/pieceset1/queenB.svg
jcchess/images/pieceset1/queenW.svg
jcchess/images/pieceset1/rookB.svg
jcchess/images/pieceset1/rookW.svg
jcchess/images/pieceset2/bishopB.svg
jcchess/images/pieceset2/bishopW.svg
jcchess/images/pieceset2/kingB.svg
jcchess/images/pieceset2/kingW.svg
jcchess/images/pieceset2/knightB.svg
jcchess/images/pieceset2/knightW.svg
jcchess/images/pieceset2/pawnB.svg
jcchess/images/pieceset2/pawnW.svg
jcchess/images/pieceset2/queenB.svg
jcchess/images/pieceset2/queenW.svg
jcchess/images/pieceset2/rookB.svg
jcchess/images/pieceset2/rookW.svg
locale/jcchess.pot
locale/en_US/LC_MESSAGES/jcchess.po